{
  "_comment": "Vision-pose source calibration. Both stack converters return `.notImplemented` in v1: AP `VISO_*` and PX4 `EKF2_EV_*` are stack-specific (sensor type, delay, noise variance differ).\n\nRegistered for discoverability — Vehicle Inspector lists it; runtime returns a precise 'not implemented in this app version' message.",
  "entryStepID": "calibrate",
  "overallBudgetSeconds": 30,
  "steps": [
    {
      "kind": "invokeCommand",
      "id": "calibrate",
      "command": "command.fleet.vehicle.do.calibrate.vision",
      "matchers": [
        {
          "when": { "kind": "success" },
          "then": { "kind": "succeed" }
        },
        {
          "when": { "kind": "error", "errorKind": "notImplemented" },
          "then": {
            "kind": "fail",
            "detail": "Vision-pose calibration is not implemented in this app version. AP `VISO_*` and PX4 `EKF2_EV_*` parameter families require a per-stack authoring pass."
          }
        },
        {
          "when": { "kind": "cancelled" },
          "then": {
            "kind": "fail",
            "detail": "Vision-pose calibration cancelled by operator."
          }
        },
        {
          "when": { "kind": "any" },
          "then": {
            "kind": "fail",
            "detail": "Vision-pose calibration failed with an unhandled outcome — see the audit trace for the underlying response."
          }
        }
      ]
    }
  ]
}
